{
  "site": "siteverdict2",
  "build_name": "sitecheck-99C-parcel-precision-p4-2026-06-04",
  "package_number": "99C",
  "build_time": "2026-06-04T00:00:00Z",
  "release_note": "Parcel precision Phase 4: near-tolerance (point within 30m of address-matched property) + SUBURB GUARD (user-typed suburb must equal matched property suburb, kills geocode-relocation wrongs). Measured on 320 stratified addresses: verified 64.0%->68.0%, exact-on-verified 100%, CONFIDENT-WRONG 0. geocode/nearby unchanged.",
  "status": "draft-awaiting-private-gate",
  "features": {
    "publicFlowTwoStep": true,
    "siteCheckRequiresLandSizeFrontage": false,
    "userEnteredLabel": true,
    "plainEnglishResultSections": true,
    "stateBReducedResult": false,
    "parcelMatchNotConfirmedWording": true,
    "executiveVerdictRetiredPublic": true,
    "institutionalScorecardRetiredPublic": true,
    "approvalConfidenceRetiredPublic": true,
    "reportGateRetiredPublic": true,
    "scoringKeptInternalOnly": true,
    "professionalReviewPage": true,
    "noUploadOnSiteCheck": true,
    "disclaimersRetained": true,
    "dataEngineUnchanged": true,
    "thankYouPage": true,
    "scorecardHeaderResidueRemoved": true,
    "realFlowStateAVerified": true,
    "staticNavNoOverlay": true,
    "nswWording": true,
    "noPublicAdvDisHeadings": true,
    "whatStillNeedsCheckingSection": true,
    "deployUnderPublicDir": true,
    "nswPositioning": true,
    "siteCheckAddressOnly": true,
    "landSizeFrontageOptional": true,
    "parcelConfidenceNeedsReviewLine": true,
    "yieldFunctionNeutralised": true,
    "noFabricatedMinLot": true,
    "r3AddressGuard": true,
    "uxTwoColumnDesktop": true,
    "largerBodyText": true,
    "widerResultDesktop": true,
    "autocompleteDeferred": true,
    "draggablePinDeferred": true,
    "nearbyContextServerSide": true,
    "nearbyFourStates": true,
    "nearbyOverpassMirrorFallback": true,
    "parcelPropertyResolution": true,
    "parcelMultiLotSummedArea": true,
    "parcelConfidenceModel": true,
    "parcelAreaConflictWarning": true,
    "parcelVerifiedRate65": true,
    "parcelStrataDetection": true,
    "parcelBufferFallback": true,
    "parcelAddressFirst": true,
    "parcelFailSafeContext": true,
    "parcelNearToleranceSuburbGuard": true,
    "parcelVerifiedRate68": true
  },
  "principle_version": "1.0"
}